latex_maker/__init__.py
latex_maker/latex_maker.py
awesome_latex_maker-0.0.3.dist-info/METADATA
awesome_latex_maker-0.0.3.dist-info/WHEEL
awesome_latex_maker-0.0.3.dist-info/top_level.txt
awesome_latex_maker-0.0.3.dist-info/RECORD
