Metadata-Version: 2.1
Name: awesome-latex-maker
Version: 0.0.3
Summary: Awesome LaTeX Maker
Author: Georgii Angeni
Requires-Python: >=3.11, <4
Requires-Dist: pdflatex
